{"fieldBBs": [{"poly_points": [[3964, 661], [4487, 668], [4481, 825], [3958, 818]], "type": "fieldP", "id": "f0", "isBlank": 1}, {"poly_points": [[5391, 701], [5796, 707], [5791, 836], [5386, 831]], "type": "fieldP", "id": "f1", "isBlank": 1}, {"poly_points": [[4886, 813], [5715, 823], [5711, 926], [4882, 916]], "type": "fieldP", "id": "f2", "isBlank": 1}, {"poly_points": [[3931, 966], [4394, 972], [4390, 1085], [3927, 1079]], "type": "fieldP", "id": "f3", "isBlank": 1}, {"poly_points": [[4672, 976], [4914, 968], [4910, 1071], [4668, 1079]], "type": "fieldP", "id": "f4", "isBlank": 1}, {"poly_points": [[5376, 988], [5844, 994], [5840, 1109], [5371, 1103]], "type": "fieldP", "id": "f5", "isBlank": 1}, {"poly_points": [[5918, 985], [6068, 987], [6063, 1117], [5913, 1115]], "type": "fieldP", "id": "f6", "isBlank": 1}, {"poly_points": [[4134, 1094], [5049, 1057], [5044, 1187], [4130, 1224]], "type": "fieldP", "id": "f7", "isBlank": 1}, {"poly_points": [[3962, 1562], [4646, 1567], [4641, 1704], [3957, 1699]], "type": "field", "id": "f8", "isBlank": 1}, {"poly_points": [[4937, 1574], [5432, 1580], [5430, 1648], [4934, 1642]], "type": "fieldP", "id": "f9", "isBlank": 1}, {"poly_points": [[5692, 1556], [6239, 1563], [6235, 1661], [5688, 1654]], "type": "fieldP", "id": "f10", "isBlank": 1}, {"poly_points": [[5091, 1786], [5304, 1769], [5300, 1879], [5088, 1895]], "type": "fieldP", "id": "f11", "isBlank": 1}, {"poly_points": [[5570, 1788], [6002, 1793], [5999, 1871], [5567, 1866]], "type": "fieldP", "id": "f12", "isBlank": 1}, {"poly_points": [[5863, 1853], [6533, 1865], [6521, 1967], [5851, 1955]], "type": "fieldP", "id": "f13", "isBlank": 1}, {"poly_points": [[3952, 2597], [5381, 2615], [5375, 2786], [3946, 2768]], "type": "fieldP", "id": "f14", "isBlank": 3}, {"poly_points": [[4210, 3441], [4527, 3445], [4524, 3516], [4208, 3512]], "type": "fieldP", "id": "f15", "isBlank": 3}, {"poly_points": [[5414, 3456], [6021, 3464], [6018, 3538], [5411, 3530]], "type": "fieldP", "id": "f16", "isBlank": 3}, {"poly_points": [[3885, 3517], [4904, 3530], [4902, 3591], [3883, 3578]], "type": "fieldP", "id": "f17", "isBlank": 3}, {"poly_points": [[3971, 3901], [5200, 3917], [5195, 4046], [3967, 4030]], "type": "fieldP", "id": "f18", "isBlank": 3}, {"poly_points": [[5511, 4607], [6049, 4614], [6047, 4685], [5508, 4678]], "type": "fieldP", "id": "f19", "isBlank": 3}, {"poly_points": [[4020, 4649], [4691, 4658], [4688, 4732], [4017, 4723]], "type": "fieldP", "id": "f20", "isBlank": 3}, {"poly_points": [[4802, 4674], [4915, 4676], [4912, 4744], [4799, 4742]], "type": "fieldP", "id": "f21", "isBlank": 3}, {"poly_points": [[1242, 227], [2211, 227], [2211, 373], [1242, 373]], "type": "comment", "id": "f22", "isBlank": 1}, {"poly_points": [[1527, 351], [2090, 351], [2090, 454], [1527, 454]], "type": "comment", "id": "f23", "isBlank": 1}, {"poly_points": [[1213, 439], [2233, 439], [2233, 644], [1213, 644]], "type": "comment", "id": "f24", "isBlank": 1}, {"poly_points": [[1154, 691], [2097, 691], [2097, 936], [1154, 936]], "type": "comment", "id": "f25", "isBlank": 1}, {"poly_points": [[5485, 1189], [6283, 1189], [6283, 1313], [5485, 1313]], "type": "comment", "id": "f26", "isBlank": 1}, {"poly_points": [[5767, 1475], [6052, 1475], [6052, 1563], [5767, 1563]], "type": "fieldP", "id": "f27", "isBlank": 1}, {"poly_points": [[5165, 2043], [6167, 2043], [6167, 2260], [5165, 2260]], "type": "comment", "id": "f28", "isBlank": 1}, {"poly_points": [[5515, 2217], [6517, 2217], [6517, 2414], [5515, 2414]], "type": "comment", "id": "f29", "isBlank": 1}], "actualPage_corners": {"bl": [163.06205031901982, 5766.934233449478], "tl": [166.21872030408713, 219.2658661025398], "tr": [6595.14455405222, 146.63246640119633], "br": [6642.681263858092, 5660.890803882528]}, "height": 5877, "labelTime": 753.9019677639008, "page_corners": {"bl": [163.06205031901982, 5766.934233449478], "tl": [166.21872030408713, 219.2658661025398], "tr": [6595.14455405222, 146.63246640119633], "br": [6642.681263858092, 5660.890803882528]}, "groups": [], "horzLinks": [["t0", "f0", "t1", "f1", "t2"], ["t3", "f2", "t4"], ["f3", "t6", "f4", "t7", "f5", "t8", "f6"], ["t9", "f7", "t10"], ["f8", "t12", "f9", "t13", "f10"], ["t16", "f11", "t17", "f12", "t18"], ["t19", "f13"], ["t22", "f15", "t23", "f16", "t24"], ["f17", "t25"], ["t31", "f19", "t32"], ["t33", "f20", "t34", "f21"]], "pairs": [["t0", "f0"], ["t1", "f0"], ["t1", "f1"], ["t2", "f1"], ["t3", "f2"], ["t4", "f2"], ["t5", "f3"], ["t6", "f3"], ["t6", "f4"], ["t7", "f4"], ["t7", "f5"], ["t8", "f5"], ["t8", "f6"], ["t9", "f6"], ["t9", "f7"], ["t10", "f7"], ["t12", "f8"], ["t12", "f9"], ["t13", "f9"], ["t13", "f10"], ["t14", "f10"], ["t16", "f11"], ["t17", "f11"], ["t17", "f12"], ["t18", "f12"], ["t19", "f13"], ["t21", "f14"], ["t22", "f14"], ["t22", "f15"], ["t23", "f15"], ["t23", "f16"], ["t24", "f16"], ["t24", "f17"], ["t25", "f17"], ["t29", "f18"], ["t30", "f18"], ["t31", "f19"], ["t32", "f19"], ["t33", "f20"], ["t34", "f20"], ["t34", "f21"], ["t11", "f27"]], "samePairs": [["t3", "t2"], ["t5", "t4"], ["t15", "t14"], ["t16", "t15"], ["t19", "t18"], ["t26", "t25"], ["t27", "t26"], ["t28", "t27"], ["t29", "t28"], ["t31", "t30"], ["t33", "t32"], ["f23", "f22"], ["f24", "f23"], ["f25", "f24"], ["t15", "t14"], ["f29", "f28"], ["f8", "f27"]], "checkedBy": ["Drake"], "width": 7606, "textBBs": [{"poly_points": [[3890, 746], [3951, 747], [3948, 820], [3887, 819]], "type": "textP", "id": "t0"}, {"poly_points": [[4579, 757], [5381, 767], [5378, 831], [4576, 821]], "type": "textP", "id": "t1"}, {"poly_points": [[5842, 768], [6210, 773], [6207, 836], [5840, 831]], "type": "textP", "id": "t2"}, {"poly_points": [[3888, 841], [4880, 854], [4878, 903], [3887, 890]], "type": "textP", "id": "t3"}, {"poly_points": [[6001, 860], [6211, 863], [6209, 919], [5999, 916]], "type": "textP", "id": "t4"}, {"poly_points": [[3883, 925], [5765, 949], [5763, 1005], [3881, 981]], "type": "textP", "id": "t5"}, {"poly_points": [[4412, 1017], [4510, 1018], [4508, 1070], [4410, 1069]], "type": "textP", "id": "t6"}, {"poly_points": [[5112, 1024], [5273, 1026], [5271, 1077], [5110, 1075]], "type": "textP", "id": "t7"}, {"poly_points": [[5874, 1013], [5943, 1014], [5941, 1070], [5872, 1069]], "type": "textP", "id": "t8"}, {"poly_points": [[3872, 1096], [4141, 1099], [4139, 1153], [3870, 1149]], "type": "textP", "id": "t9"}, {"poly_points": [[5084, 1096], [5301, 1099], [5299, 1146], [5083, 1143]], "type": "textP", "id": "t10"}, {"poly_points": [[3892, 1496], [5715, 1520], [5712, 1594], [3889, 1570]], "type": "textP", "id": "t11"}, {"poly_points": [[4731, 1590], [4785, 1591], [4783, 1648], [4729, 1647]], "type": "textP", "id": "t12"}, {"poly_points": [[5448, 1587], [5644, 1590], [5642, 1636], [5446, 1633]], "type": "textP", "id": "t13"}, {"poly_points": [[4559, 1662], [5865, 1661], [5863, 1715], [4557, 1716]], "type": "textP", "id": "t14"}, {"poly_points": [[4497, 1732], [6233, 1735], [6230, 1794], [4495, 1791]], "type": "textP", "id": "t15"}, {"poly_points": [[4669, 1805], [4948, 1809], [4946, 1868], [4667, 1864]], "type": "textP", "id": "t16"}, {"poly_points": [[5410, 1808], [5584, 1810], [5582, 1871], [5408, 1869]], "type": "textP", "id": "t17"}, {"poly_points": [[6058, 1807], [6222, 1809], [6220, 1856], [6056, 1854]], "type": "textP", "id": "t18"}, {"poly_points": [[4667, 1871], [5846, 1886], [5844, 1950], [4664, 1935]], "type": "textP", "id": "t19"}, {"poly_points": [[3885, 2497], [5452, 2499], [5449, 2573], [3882, 2571]], "type": "textP", "id": "t21"}, {"poly_points": [[3878, 3446], [4197, 3450], [4195, 3511], [3875, 3507]], "type": "textP", "id": "t22"}, {"poly_points": [[4527, 3448], [5409, 3434], [5407, 3496], [4524, 3510]], "type": "textP", "id": "t23"}, {"poly_points": [[6024, 3448], [6225, 3451], [6223, 3506], [6022, 3503]], "type": "textP", "id": "t24"}, {"poly_points": [[4914, 3518], [6217, 3515], [6215, 3566], [4912, 3570]], "type": "textP", "id": "t25"}, {"poly_points": [[3877, 3584], [6231, 3576], [6228, 3638], [3874, 3646]], "type": "textP", "id": "t26"}, {"poly_points": [[3880, 3646], [6222, 3656], [6220, 3730], [3878, 3720]], "type": "textP", "id": "t27"}, {"poly_points": [[3874, 3729], [6243, 3725], [6240, 3790], [3872, 3794]], "type": "textP", "id": "t28"}, {"poly_points": [[3865, 3800], [4072, 3803], [4070, 3861], [3863, 3858]], "type": "textP", "id": "t29"}, {"poly_points": [[3861, 4509], [4921, 4520], [4919, 4590], [3858, 4579]], "type": "textP", "id": "t30"}, {"poly_points": [[4049, 4584], [5517, 4586], [5515, 4649], [4047, 4648]], "type": "textP", "id": "t31"}, {"poly_points": [[6118, 4596], [6215, 4597], [6212, 4674], [6115, 4673]], "type": "textP", "id": "t32"}, {"poly_points": [[3873, 4656], [3935, 4657], [3933, 4722], [3870, 4721]], "type": "textP", "id": "t33"}, {"poly_points": [[4706, 4647], [4786, 4648], [4784, 4713], [4704, 4712]], "type": "textP", "id": "t34"}], "imageFilename": "100788105_00015.jpg", "transcriptions": {"f8": "Cayenne", "f7": "J Frank Walton OPA", "f10": "keen", "f5": "May", "f11": "9th", "f24": "May 9-1873", "f3": "Sworn", "f22": "Sch Cayeune", "f28": "J. Frank waltor", "f26": "W.S. Keene ", "f2": "Ic Cayenne", "f0": "W Skeen", "f23": "Keane", "f4": "9th", "f1": "Rwcar", "f6": "873", "f25": "Feruary", "f27": "AC", "f12": "May", "f13": "Twenty Three", "f29": "\u00bfP Dy. Collector.", "f9": "Salem"}}