{"fieldBBs": [{"poly_points": [[1316, 200], [1628, 200], [1628, 258], [1316, 258]], "type": "field", "id": "f0", "isBlank": 2}, {"poly_points": [[927, 354], [1567, 354], [1567, 433], [927, 433]], "type": "field", "id": "f1", "isBlank": 1}, {"poly_points": [[1041, 436], [1456, 436], [1456, 528], [1041, 528]], "type": "field", "id": "f2", "isBlank": 1}, {"poly_points": [[870, 539], [960, 539], [960, 604], [870, 604]], "type": "field", "id": "f3", "isBlank": 1}, {"poly_points": [[1030, 528], [1332, 528], [1332, 605], [1030, 605]], "type": "field", "id": "f4", "isBlank": 1}, {"poly_points": [[1426, 531], [1475, 531], [1475, 605], [1426, 605]], "type": "field", "id": "f5", "isBlank": 1}, {"poly_points": [[1615, 531], [1710, 531], [1710, 608], [1615, 608]], "type": "field", "id": "f6", "isBlank": 1}, {"poly_points": [[914, 608], [1393, 608], [1393, 698], [914, 698]], "type": "field", "id": "f7", "isBlank": 1}, {"poly_points": [[1511, 612], [1688, 612], [1688, 692], [1511, 692]], "type": "field", "id": "f8", "isBlank": 1}, {"poly_points": [[1062, 708], [1261, 708], [1261, 800], [1062, 800]], "type": "field", "id": "f9", "isBlank": 1}, {"poly_points": [[1429, 692], [1707, 692], [1707, 750], [1429, 750]], "type": "field", "id": "f10", "isBlank": 2}, {"poly_points": [[48, 31], [735, 31], [735, 641], [48, 641]], "type": "graphic", "id": "f11", "isBlank": 1}, {"poly_points": [[503, 249], [927, 172], [933, 214], [519, 386]], "type": "comment", "id": "f12", "isBlank": 4}, {"poly_points": [[141, 655], [766, 655], [766, 748], [141, 748]], "type": "field", "id": "f13", "isBlank": 1}, {"poly_points": [[207, 798], [433, 798], [433, 867], [207, 867]], "type": "field", "id": "f15", "isBlank": 1}, {"poly_points": [[460, 803], [598, 803], [598, 872], [460, 872]], "type": "field", "id": "f16", "isBlank": 1}, {"poly_points": [[629, 798], [775, 798], [775, 871], [629, 871]], "type": "field", "id": "f17", "isBlank": 1}, {"poly_points": [[315, 863], [589, 863], [589, 932], [315, 932]], "type": "field", "id": "f18", "isBlank": 2}, {"poly_points": [[315, 922], [618, 922], [618, 1011], [315, 1011]], "type": "field", "id": "f19", "isBlank": 1}, {"poly_points": [[1004, 884], [1678, 884], [1678, 969], [1004, 969]], "type": "field", "id": "f20", "isBlank": 1}, {"poly_points": [[907, 964], [1466, 964], [1466, 1053], [907, 1053]], "type": "comment", "id": "f21", "isBlank": 2}], "actualPage_corners": {"bl": [39.761463819127215, 1050.1579897835309], "tl": [39.712131056969284, 38.918598157240496], "tr": [1739.7649362734494, 40.89430547199962], "br": [1743.2870266748994, 1052.8440295755788]}, "height": 1096, "labelTime": 118.5102310180664, "page_corners": {"bl": [39.761463819127215, 1050.1579897835309], "tl": [39.712131056969284, 38.918598157240496], "tr": [1739.7649362734494, 40.89430547199962], "br": [1743.2870266748994, 1052.8440295755788]}, "groups": [], "horzLinks": [["t2", "f0"], ["t6", "f1"], ["t8", "f2"], ["t9", "f3", "t10", "f4", "t11", "f5", "t12", "f6"], ["t13", "f7", "t14", "f8"], ["t15", "f9", "t16", "f10"], ["t21", "f15", "f16", "f17"], ["t22", "f18"], ["t23", "f19"]], "pairs": [["t2", "f0"], ["t6", "f1"], ["t8", "f2"], ["t9", "f3"], ["t10", "f3"], ["t10", "f4"], ["t11", "f4"], ["t11", "f5"], ["t12", "f6"], ["t13", "f7"], ["t14", "f8"], ["t15", "f9"], ["t16", "f10"], ["t22", "f18"], ["t23", "f19"], ["t27", "f20"], ["t17", "f11"], ["t21", "f15"], ["t18", "f15"], ["t19", "f16"], ["t20", "f17"]], "samePairs": [["t1", "t0"], ["t4", "t3"], ["t5", "t4"], ["t25", "t24"], ["t26", "t25"], ["f16", "f15"], ["f17", "f16"]], "checkedBy": ["Drake"], "width": 1786, "textBBs": [{"poly_points": [[901, 63], [1617, 63], [1617, 129], [901, 129]], "type": "text", "id": "t0"}, {"poly_points": [[857, 135], [1649, 135], [1649, 187], [857, 187]], "type": "text", "id": "t1"}, {"poly_points": [[1125, 225], [1260, 225], [1260, 272], [1125, 272]], "type": "text", "id": "t2"}, {"poly_points": [[865, 277], [1709, 277], [1709, 309], [865, 309]], "type": "textInst", "id": "t3"}, {"poly_points": [[798, 304], [1720, 304], [1720, 333], [798, 333]], "type": "textInst", "id": "t4"}, {"poly_points": [[798, 335], [1450, 335], [1450, 357], [798, 357]], "type": "textInst", "id": "t5"}, {"poly_points": [[793, 396], [917, 396], [917, 443], [793, 443]], "type": "text", "id": "t6"}, {"poly_points": [[777, 484], [988, 484], [988, 528], [777, 528]], "type": "text", "id": "t8"}, {"poly_points": [[795, 571], [867, 571], [867, 613], [795, 613]], "type": "text", "id": "t9"}, {"poly_points": [[967, 576], [1012, 576], [1012, 607], [967, 607]], "type": "text", "id": "t10"}, {"poly_points": [[1351, 562], [1422, 562], [1422, 610], [1351, 610]], "type": "text", "id": "t11"}, {"poly_points": [[1479, 563], [1604, 563], [1604, 607], [1479, 607]], "type": "text", "id": "t12"}, {"poly_points": [[783, 644], [912, 644], [912, 695], [783, 695]], "type": "text", "id": "t13"}, {"poly_points": [[1393, 645], [1488, 645], [1488, 692], [1393, 692]], "type": "text", "id": "t14"}, {"poly_points": [[801, 729], [1047, 729], [1047, 779], [801, 779]], "type": "text", "id": "t15"}, {"poly_points": [[1253, 735], [1487, 735], [1487, 784], [1253, 784]], "type": "text", "id": "t16"}, {"poly_points": [[230, 631], [571, 631], [571, 661], [230, 661]], "type": "textMinor", "id": "t17"}, {"poly_points": [[222, 763], [415, 763], [415, 793], [222, 793]], "type": "textMinor", "id": "t18"}, {"poly_points": [[495, 766], [569, 766], [569, 797], [495, 797]], "type": "textMinor", "id": "t19"}, {"poly_points": [[658, 764], [735, 764], [735, 795], [658, 795]], "type": "textMinor", "id": "t20"}, {"poly_points": [[67, 801], [199, 801], [199, 859], [67, 859]], "type": "text", "id": "t21"}, {"poly_points": [[80, 892], [161, 892], [161, 930], [80, 930]], "type": "text", "id": "t22"}, {"poly_points": [[70, 962], [202, 962], [202, 1017], [70, 1017]], "type": "text", "id": "t23"}, {"poly_points": [[861, 801], [1715, 801], [1715, 835], [861, 835]], "type": "textP", "id": "t24"}, {"poly_points": [[799, 829], [1722, 829], [1722, 859], [799, 859]], "type": "textP", "id": "t25"}, {"poly_points": [[799, 856], [1173, 856], [1173, 885], [799, 885]], "type": "textP", "id": "t26"}, {"poly_points": [[1277, 970], [1654, 970], [1654, 1004], [1277, 1004]], "type": "text", "id": "t27"}, {"poly_points": [[787, 1006], [994, 1006], [994, 1049], [787, 1049]], "type": "text", "id": "t28"}], "imageFilename": "100176369_00011.jpg", "transcriptions": {"f17": "Black", "f12": "G.william", "f18": "12937", "f7": "S.S Mouton", "f13": "Wellbert Ross", "f20": "J.J Sullivan", "f8": "Bu", "f6": "5/7", "f2": "British", "f16": "Black", "f15": "Med", "f10": "BOSTON", "f0": "BOSTON", "f4": "Mch 23", "f5": "8", "f19": "7/27/18", "f1": "Ross Dellert", "f21": "Collector ", "f9": "\u00ab7/27/10\u00bb", "f3": "35"}}