{"fieldBBs": [{"poly_points": [[1212, 574], [1566, 574], [1566, 638], [1212, 638]], "type": "field", "id": "f0", "isBlank": 1}, {"poly_points": [[1675, 579], [1833, 579], [1833, 639], [1675, 639]], "type": "field", "id": "f1", "isBlank": 1}, {"poly_points": [[1898, 602], [1935, 602], [1935, 639], [1898, 639]], "type": "field", "id": "f2", "isBlank": 1}, {"poly_points": [[494, 688], [1114, 688], [1114, 757], [494, 757]], "type": "field", "id": "f3", "isBlank": 1}, {"poly_points": [[1269, 705], [1410, 705], [1410, 737], [1269, 737]], "type": "fieldCircle", "id": "f4", "isBlank": 1}, {"poly_points": [[1262, 745], [1426, 745], [1426, 779], [1262, 779]], "type": "fieldCircle", "id": "f5", "isBlank": 1}, {"poly_points": [[1711, 639], [1907, 639], [1907, 707], [1711, 707]], "type": "field", "id": "f6", "isBlank": 2}, {"poly_points": [[1672, 732], [1881, 732], [1881, 784], [1672, 784]], "type": "field", "id": "f7", "isBlank": 1}, {"poly_points": [[714, 758], [940, 758], [940, 829], [714, 829]], "type": "field", "id": "f8", "isBlank": 1}, {"poly_points": [[1335, 789], [1537, 787], [1537, 828], [1335, 830]], "type": "field", "id": "f9", "isBlank": 3}, {"poly_points": [[676, 839], [1048, 839], [1048, 907], [676, 907]], "type": "field", "id": "f10", "isBlank": 1}, {"poly_points": [[1174, 846], [1557, 846], [1557, 909], [1174, 909]], "type": "field", "id": "f11", "isBlank": 1}, {"poly_points": [[1672, 830], [1743, 830], [1743, 873], [1672, 873]], "type": "field", "id": "f12", "isBlank": 3}, {"poly_points": [[1711, 901], [1780, 901], [1780, 944], [1711, 944]], "type": "field", "id": "f13", "isBlank": 1}, {"poly_points": [[722, 991], [938, 991], [938, 1058], [722, 1058]], "type": "fieldP", "id": "f14", "isBlank": 1}, {"poly_points": [[984, 1023], [1026, 1023], [1026, 1063], [984, 1063]], "type": "fieldP", "id": "f15", "isBlank": 1}, {"poly_points": [[1608, 984], [1908, 984], [1908, 1017], [1608, 1017]], "type": "fieldP", "id": "f16", "isBlank": 3}, {"poly_points": [[1540, 1058], [1918, 1056], [1918, 1095], [1540, 1097]], "type": "fieldP", "id": "f17", "isBlank": 3}, {"poly_points": [[1639, 1107], [1817, 1107], [1817, 1167], [1639, 1167]], "type": "field", "id": "f18", "isBlank": 1}, {"poly_points": [[551, 1191], [901, 1191], [901, 1242], [551, 1242]], "type": "fieldP", "id": "f19", "isBlank": 1}, {"poly_points": [[1109, 1194], [1399, 1194], [1399, 1246], [1109, 1246]], "type": "field", "id": "f20", "isBlank": 1}, {"poly_points": [[1623, 1202], [2092, 1204], [2092, 1253], [1623, 1250]], "type": "field", "id": "f21", "isBlank": 1}, {"poly_points": [[718, 1273], [991, 1273], [991, 1324], [718, 1324]], "type": "field", "id": "f22", "isBlank": 1}, {"poly_points": [[1494, 1250], [1797, 1250], [1797, 1325], [1494, 1325]], "type": "field", "id": "f23", "isBlank": 1}, {"poly_points": [[715, 1343], [1297, 1343], [1297, 1406], [715, 1406]], "type": "field", "id": "f24", "isBlank": 1}, {"poly_points": [[1425, 1374], [1550, 1374], [1550, 1403], [1425, 1403]], "type": "fieldCircle", "id": "f25", "isBlank": 1}, {"poly_points": [[1560, 1373], [1656, 1373], [1656, 1403], [1560, 1403]], "type": "fieldCircle", "id": "f26", "isBlank": 1}, {"poly_points": [[1656, 1374], [1780, 1374], [1780, 1406], [1656, 1406]], "type": "fieldCircle", "id": "f27", "isBlank": 1}, {"poly_points": [[1781, 1373], [1935, 1373], [1935, 1404], [1781, 1404]], "type": "fieldCircle", "id": "f28", "isBlank": 1}, {"poly_points": [[524, 1426], [751, 1426], [751, 1478], [524, 1478]], "type": "field", "id": "f29", "isBlank": 1}, {"poly_points": [[1284, 1422], [1420, 1422], [1420, 1479], [1284, 1479]], "type": "field", "id": "f30", "isBlank": 1}, {"poly_points": [[1803, 1420], [1928, 1420], [1928, 1476], [1803, 1476]], "type": "field", "id": "f31", "isBlank": 1}, {"poly_points": [[846, 1540], [935, 1540], [935, 1574], [846, 1574]], "type": "fieldCircle", "id": "f32", "isBlank": 1}, {"poly_points": [[840, 1586], [961, 1586], [961, 1614], [840, 1614]], "type": "fieldCircle", "id": "f33", "isBlank": 1}, {"poly_points": [[1112, 1534], [1197, 1534], [1197, 1590], [1112, 1590]], "type": "field", "id": "f34", "isBlank": 1}, {"poly_points": [[1344, 1543], [1439, 1543], [1439, 1594], [1344, 1594]], "type": "field", "id": "f35", "isBlank": 1}, {"poly_points": [[1724, 1541], [1855, 1541], [1855, 1597], [1724, 1597]], "type": "field", "id": "f36", "isBlank": 1}, {"poly_points": [[761, 1692], [1981, 1692], [1981, 1744], [761, 1744]], "type": "field", "id": "f37", "isBlank": 1}, {"poly_points": [[393, 1544], [743, 1544], [743, 1944], [393, 1944]], "type": "graphic", "id": "f38", "isBlank": 1}, {"poly_points": [[622, 1968], [1371, 1974], [1371, 2014], [622, 2008]], "type": "field", "id": "f39", "isBlank": 3}, {"poly_points": [[618, 2043], [1911, 2047], [1911, 2087], [618, 2083]], "type": "field", "id": "f40", "isBlank": 3}, {"poly_points": [[476, 2198], [993, 2195], [993, 2247], [476, 2250]], "type": "field", "id": "f41", "isBlank": 3}, {"poly_points": [[1405, 2195], [1931, 2194], [1931, 2250], [1405, 2251]], "type": "field", "id": "f42", "isBlank": 3}, {"poly_points": [[635, 2352], [1117, 2352], [1117, 2403], [635, 2403]], "type": "field", "id": "f43", "isBlank": 3}, {"poly_points": [[1298, 2341], [1468, 2341], [1468, 2412], [1298, 2412]], "type": "field", "id": "f44", "isBlank": 1}, {"poly_points": [[1691, 2358], [1800, 2358], [1800, 2389], [1691, 2389]], "type": "fieldCircle", "id": "f45", "isBlank": 1}, {"poly_points": [[1686, 2396], [1829, 2396], [1829, 2430], [1686, 2430]], "type": "fieldCircle", "id": "f46", "isBlank": 1}, {"poly_points": [[659, 2406], [846, 2406], [846, 2442], [659, 2442]], "type": "field", "id": "f47", "isBlank": 3}, {"poly_points": [[1131, 2425], [1409, 2425], [1409, 2478], [1131, 2478]], "type": "field", "id": "f48", "isBlank": 2}, {"poly_points": [[1658, 2432], [1902, 2432], [1902, 2485], [1658, 2485]], "type": "field", "id": "f49", "isBlank": 1}, {"poly_points": [[1084, 2478], [1403, 2478], [1403, 2522], [1084, 2522]], "type": "field", "id": "f50", "isBlank": 2}, {"poly_points": [[1678, 2483], [1905, 2483], [1905, 2524], [1678, 2524]], "type": "field", "id": "f51", "isBlank": 1}, {"poly_points": [[892, 2516], [1511, 2515], [1511, 2551], [892, 2552]], "type": "field", "id": "f52", "isBlank": 3}, {"poly_points": [[1622, 2529], [1924, 2529], [1924, 2556], [1622, 2556]], "type": "field", "id": "f53", "isBlank": 3}, {"poly_points": [[989, 1818], [1064, 1818], [1064, 1851], [989, 1851]], "type": "fieldCircle", "id": "f55", "isBlank": 1}, {"poly_points": [[1069, 1819], [1199, 1819], [1199, 1854], [1069, 1854]], "type": "fieldCircle", "id": "f56", "isBlank": 1}, {"poly_points": [[1197, 1823], [1440, 1823], [1440, 1852], [1197, 1852]], "type": "fieldCircle", "id": "f57", "isBlank": 1}, {"poly_points": [[1444, 1823], [1563, 1823], [1563, 1854], [1444, 1854]], "type": "fieldCircle", "id": "f58", "isBlank": 1}, {"poly_points": [[1560, 1819], [1743, 1819], [1743, 1851], [1560, 1851]], "type": "fieldCircle", "id": "f59", "isBlank": 1}, {"poly_points": [[1742, 1816], [1870, 1816], [1870, 1846], [1742, 1846]], "type": "fieldCircle", "id": "f60", "isBlank": 1}, {"poly_points": [[986, 1868], [1072, 1868], [1072, 1896], [986, 1896]], "type": "fieldCircle", "id": "f61", "isBlank": 1}, {"poly_points": [[1080, 1863], [1171, 1863], [1171, 1896], [1080, 1896]], "type": "fieldCircle", "id": "f62", "isBlank": 1}, {"poly_points": [[1175, 1865], [1307, 1865], [1307, 1898], [1175, 1898]], "type": "fieldCircle", "id": "f63", "isBlank": 1}, {"poly_points": [[1308, 1868], [1383, 1868], [1383, 1898], [1308, 1898]], "type": "fieldCircle", "id": "f64", "isBlank": 1}, {"poly_points": [[1380, 1860], [1441, 1860], [1441, 1896], [1380, 1896]], "type": "fieldCircle", "id": "f65", "isBlank": 1}, {"poly_points": [[1449, 1863], [1537, 1863], [1537, 1896], [1449, 1896]], "type": "fieldCircle", "id": "f66", "isBlank": 1}, {"poly_points": [[1549, 1859], [1648, 1859], [1648, 1896], [1549, 1896]], "type": "fieldCircle", "id": "f67", "isBlank": 1}, {"poly_points": [[974, 1907], [1099, 1907], [1099, 1942], [974, 1942]], "type": "fieldCircle", "id": "f68", "isBlank": 1}, {"poly_points": [[1094, 1909], [1182, 1909], [1182, 1940], [1094, 1940]], "type": "fieldCircle", "id": "f69", "isBlank": 1}, {"poly_points": [[1186, 1909], [1261, 1909], [1261, 1940], [1186, 1940]], "type": "fieldCircle", "id": "f70", "isBlank": 1}, {"poly_points": [[1265, 1907], [1360, 1907], [1360, 1942], [1265, 1942]], "type": "fieldCircle", "id": "f71", "isBlank": 1}], "actualPage_corners": {"bl": [254.0667113256856, 2722.669736135639], "tl": [259.8410689989025, 313.0867731439254], "tr": [2098.6162397106364, 316.4178315986038], "br": [2100.2036863845096, 2727.8315574589947]}, "height": 3035, "labelTime": 256.0561079978943, "page_corners": {"bl": [254.0667113256856, 2722.669736135639], "tl": [259.8410689989025, 313.0867731439254], "tr": [2098.6162397106364, 316.4178315986038], "br": [2100.2036863845096, 2727.8315574589947]}, "groups": [], "horzLinks": [["t7", "f3"], ["f0", "t5", "f1", "t6", "f2"], ["t9", "f6"], ["t10", "f7"], ["t11", "f8", "t12", "f9"], ["t13", "f10", "t15", "f11", "t16"], ["f12", "t18"], ["t19", "f13", "t20"], ["t21", "f14", "t22", "f15", "t23"], ["t24", "f16"], ["t25", "f17"], ["t26", "f18"], ["t29", "f19", "t30", "f20", "t32", "f21"], ["t33", "f22", "t34", "f23"], ["t35", "f24", "f25", "f26", "f27", "f28"], ["t37", "f29", "t39", "f30", "t40", "f31"], ["t42", "t43", "f34", "t44", "f35", "t45", "t46", "f36", "t47"], ["t53", "f39", "t54"], ["t55", "f40"], ["t60", "f43", "t61", "f44", "t62"], ["t65", "f48", "t66", "f49"], ["t67", "f50", "t68", "f51"], ["t69", "f52", "t70", "f53"], ["t77", "f68", "f69", "f70", "f71"], ["t76", "f61", "f62", "f63", "f64", "f65", "f66", "f67"], ["t75", "f55", "f56", "f57", "f58", "f59", "f60"]], "pairs": [["t5", "f0"], ["t6", "f1"], ["t6", "f2"], ["t7", "f3"], ["t9", "f6"], ["t10", "f7"], ["t11", "f8"], ["t12", "f9"], ["t13", "f10"], ["t14", "f10"], ["t15", "f10"], ["t15", "f11"], ["t16", "f11"], ["t17", "f11"], ["t18", "f12"], ["t19", "f13"], ["t20", "f13"], ["t21", "f14"], ["t22", "f14"], ["t22", "f15"], ["t23", "f15"], ["t24", "f16"], ["t25", "f17"], ["t27", "f14"], ["t26", "f18"], ["t28", "f18"], ["t29", "f19"], ["t30", "f20"], ["t31", "f20"], ["t32", "f21"], ["t33", "f22"], ["t34", "f23"], ["t35", "f24"], ["t36", "f25"], ["t36", "f26"], ["t36", "f27"], ["t36", "f28"], ["t37", "f29"], ["t38", "f29"], ["t39", "f30"], ["t40", "f31"], ["t42", "f32"], ["t42", "f33"], ["t43", "f34"], ["t44", "f34"], ["t44", "f35"], ["t45", "f35"], ["t46", "f36"], ["t47", "f36"], ["t48", "f37"], ["t53", "f39"], ["t55", "f40"], ["t56", "f41"], ["t56", "f42"], ["t57", "f41"], ["t58", "f42"], ["t60", "f43"], ["t61", "f44"], ["t62", "f46"], ["t62", "f45"], ["t63", "f47"], ["t64", "f47"], ["t65", "f48"], ["t66", "f48"], ["t66", "f49"], ["t67", "f50"], ["t68", "f50"], ["t68", "f51"], ["t69", "f52"], ["t70", "f52"], ["t70", "f53"], ["t16", "f12"], ["t75", "f55"], ["t76", "f61"], ["t77", "f68"]], "samePairs": [["t54", "t55"], ["t72", "t71"], ["t73", "t72"], ["t74", "t73"], ["t23", "t24"], ["t25", "t23"], ["t9", "t8"], ["t10", "t8"], ["t19", "t16"], ["f5", "f4"], ["f33", "f32"], ["f26", "f25"], ["f27", "f26"], ["f27", "f28"], ["f46", "f45"], ["f59", "f60"], ["f58", "f59"], ["f57", "f58"], ["f56", "f57"], ["f55", "f56"], ["f62", "f61"], ["f63", "f62"], ["f64", "f63"], ["f65", "f64"], ["f66", "f65"], ["f67", "f66"], ["f70", "f71"], ["f69", "f70"], ["f68", "f69"]], "checkedBy": [], "width": 2628, "textBBs": [{"poly_points": [[1779, 427], [1871, 427], [1871, 453], [1779, 453]], "type": "text", "id": "t0"}, {"poly_points": [[934, 420], [1380, 420], [1380, 472], [934, 472]], "type": "text", "id": "t1"}, {"poly_points": [[655, 476], [1663, 476], [1663, 531], [655, 531]], "type": "text", "id": "t2"}, {"poly_points": [[983, 530], [1327, 530], [1327, 553], [983, 553]], "type": "textMinor", "id": "t3"}, {"poly_points": [[379, 643], [1203, 643], [1203, 688], [379, 688]], "type": "text", "id": "t4"}, {"poly_points": [[1580, 604], [1655, 604], [1655, 640], [1580, 640]], "type": "text", "id": "t5"}, {"poly_points": [[1849, 606], [1898, 606], [1898, 635], [1849, 635]], "type": "text", "id": "t6"}, {"poly_points": [[394, 727], [471, 727], [471, 754], [394, 754]], "type": "text", "id": "t7"}, {"poly_points": [[1439, 720], [1580, 720], [1580, 754], [1439, 754]], "type": "text", "id": "t8"}, {"poly_points": [[1597, 679], [1665, 679], [1665, 718], [1597, 718]], "type": "text", "id": "t9"}, {"poly_points": [[1591, 764], [1662, 764], [1662, 794], [1591, 794]], "type": "text", "id": "t10"}, {"poly_points": [[380, 802], [515, 802], [515, 830], [380, 830]], "type": "text", "id": "t11"}, {"poly_points": [[1186, 790], [1312, 790], [1312, 836], [1186, 836]], "type": "text", "id": "t12"}, {"poly_points": [[383, 866], [653, 866], [653, 911], [383, 911]], "type": "text", "id": "t13"}, {"poly_points": [[806, 907], [884, 907], [884, 934], [806, 934]], "type": "textMinor", "id": "t14"}, {"poly_points": [[1045, 881], [1084, 881], [1084, 911], [1045, 911]], "type": "text", "id": "t15"}, {"poly_points": [[1607, 881], [1650, 881], [1650, 908], [1607, 908]], "type": "text", "id": "t16"}, {"poly_points": [[1266, 909], [1404, 909], [1404, 932], [1266, 932]], "type": "textMinor", "id": "t17"}, {"poly_points": [[1757, 835], [1935, 835], [1935, 868], [1757, 868]], "type": "text", "id": "t18"}, {"poly_points": [[1666, 915], [1701, 915], [1701, 948], [1666, 948]], "type": "text", "id": "t19"}, {"poly_points": [[1779, 911], [1930, 911], [1930, 945], [1779, 945]], "type": "text", "id": "t20"}, {"poly_points": [[386, 1035], [704, 1035], [704, 1061], [386, 1061]], "type": "textP", "id": "t21"}, {"poly_points": [[937, 1032], [983, 1032], [983, 1061], [937, 1061]], "type": "textP", "id": "t22"}, {"poly_points": [[1038, 1026], [1337, 1026], [1337, 1056], [1038, 1056]], "type": "textP", "id": "t23"}, {"poly_points": [[1355, 994], [1622, 994], [1622, 1025], [1355, 1025]], "type": "textP", "id": "t24"}, {"poly_points": [[1353, 1068], [1544, 1068], [1544, 1099], [1353, 1099]], "type": "textP", "id": "t25"}, {"poly_points": [[379, 1135], [1603, 1135], [1603, 1176], [379, 1176]], "type": "text", "id": "t26"}, {"poly_points": [[789, 1061], [859, 1061], [859, 1088], [789, 1088]], "type": "textMinor", "id": "t27"}, {"poly_points": [[1701, 1174], [1823, 1174], [1823, 1202], [1701, 1202]], "type": "textMinor", "id": "t28"}, {"poly_points": [[386, 1219], [531, 1219], [531, 1253], [386, 1253]], "type": "text", "id": "t29"}, {"poly_points": [[922, 1217], [1105, 1217], [1105, 1248], [922, 1248]], "type": "text", "id": "t30"}, {"poly_points": [[1094, 1256], [1380, 1256], [1380, 1278], [1094, 1278]], "type": "textMinor", "id": "t31"}, {"poly_points": [[1391, 1219], [1584, 1219], [1584, 1246], [1391, 1246]], "type": "text", "id": "t32"}, {"poly_points": [[386, 1295], [650, 1295], [650, 1335], [386, 1335]], "type": "text", "id": "t33"}, {"poly_points": [[1186, 1289], [1453, 1289], [1453, 1332], [1186, 1332]], "type": "text", "id": "t34"}, {"poly_points": [[393, 1370], [658, 1370], [658, 1407], [393, 1407]], "type": "text", "id": "t35"}, {"poly_points": [[1507, 1404], [1835, 1404], [1835, 1426], [1507, 1426]], "type": "textInst", "id": "t36"}, {"poly_points": [[384, 1450], [466, 1450], [466, 1478], [384, 1478]], "type": "text", "id": "t37"}, {"poly_points": [[534, 1481], [774, 1481], [774, 1507], [534, 1507]], "type": "textMinor", "id": "t38"}, {"poly_points": [[895, 1446], [1214, 1446], [1214, 1484], [895, 1484]], "type": "text", "id": "t39"}, {"poly_points": [[1476, 1448], [1748, 1448], [1748, 1484], [1476, 1484]], "type": "text", "id": "t40"}, {"poly_points": [[1131, 1498], [1586, 1498], [1586, 1528], [1131, 1528]], "type": "textInst", "id": "t41"}, {"poly_points": [[783, 1564], [849, 1564], [849, 1602], [783, 1602]], "type": "text", "id": "t42"}, {"poly_points": [[971, 1560], [1066, 1560], [1066, 1597], [971, 1597]], "type": "text", "id": "t43"}, {"poly_points": [[1239, 1561], [1291, 1561], [1291, 1599], [1239, 1599]], "type": "text", "id": "t44"}, {"poly_points": [[1481, 1567], [1540, 1567], [1540, 1596], [1481, 1596]], "type": "text", "id": "t45"}, {"poly_points": [[1558, 1558], [1663, 1558], [1663, 1599], [1558, 1599]], "type": "text", "id": "t46"}, {"poly_points": [[1871, 1563], [1934, 1563], [1934, 1596], [1871, 1596]], "type": "text", "id": "t47"}, {"poly_points": [[786, 1637], [1892, 1637], [1892, 1673], [786, 1673]], "type": "text", "id": "t48"}, {"poly_points": [[1122, 1780], [1509, 1780], [1509, 1816], [1122, 1816]], "type": "textInst", "id": "t49"}, {"poly_points": [[389, 1977], [622, 1977], [622, 2014], [389, 2014]], "type": "text", "id": "t53"}, {"poly_points": [[1400, 1987], [1932, 1987], [1932, 2017], [1400, 2017]], "type": "text", "id": "t54"}, {"poly_points": [[387, 2065], [612, 2065], [612, 2092], [387, 2092]], "type": "text", "id": "t55"}, {"poly_points": [[370, 2145], [738, 2145], [738, 2190], [370, 2190]], "type": "text", "id": "t56"}, {"poly_points": [[627, 2250], [848, 2250], [848, 2283], [627, 2283]], "type": "textMinor", "id": "t57"}, {"poly_points": [[1482, 2258], [1819, 2258], [1819, 2285], [1482, 2285]], "type": "textMinor", "id": "t58"}, {"poly_points": [[885, 2312], [1471, 2312], [1471, 2341], [885, 2341]], "type": "textInst", "id": "t59"}, {"poly_points": [[390, 2377], [639, 2377], [639, 2410], [390, 2410]], "type": "text", "id": "t60"}, {"poly_points": [[1131, 2370], [1268, 2370], [1268, 2412], [1131, 2412]], "type": "text", "id": "t61"}, {"poly_points": [[1832, 2378], [1930, 2378], [1930, 2413], [1832, 2413]], "type": "text", "id": "t62"}, {"poly_points": [[387, 2410], [642, 2410], [642, 2442], [387, 2442]], "type": "text", "id": "t63"}, {"poly_points": [[849, 2414], [950, 2414], [950, 2446], [849, 2446]], "type": "text", "id": "t64"}, {"poly_points": [[383, 2453], [1061, 2453], [1061, 2486], [383, 2486]], "type": "text", "id": "t65"}, {"poly_points": [[1512, 2450], [1625, 2450], [1625, 2483], [1512, 2483]], "type": "text", "id": "t66"}, {"poly_points": [[389, 2489], [882, 2489], [882, 2524], [389, 2524]], "type": "text", "id": "t67"}, {"poly_points": [[1514, 2494], [1626, 2494], [1626, 2522], [1514, 2522]], "type": "text", "id": "t68"}, {"poly_points": [[392, 2528], [889, 2528], [889, 2555], [392, 2555]], "type": "text", "id": "t69"}, {"poly_points": [[1520, 2531], [1629, 2531], [1629, 2563], [1520, 2563]], "type": "text", "id": "t70"}, {"poly_points": [[432, 2573], [1917, 2577], [1917, 2597], [432, 2593]], "type": "textInst", "id": "t71"}, {"poly_points": [[377, 2590], [1915, 2596], [1915, 2616], [377, 2610]], "type": "textInst", "id": "t72"}, {"poly_points": [[374, 2607], [1912, 2613], [1912, 2633], [374, 2627]], "type": "textInst", "id": "t73"}, {"poly_points": [[384, 2630], [602, 2630], [602, 2658], [384, 2658]], "type": "textInst", "id": "t74"}, {"poly_points": [[795, 1816], [978, 1816], [978, 1854], [795, 1854]], "type": "text", "id": "t75"}, {"poly_points": [[794, 1862], [978, 1862], [978, 1899], [794, 1899]], "type": "text", "id": "t76"}, {"poly_points": [[780, 1907], [969, 1907], [969, 1938], [780, 1938]], "type": "text", "id": "t77"}], "imageFilename": "100194510_00001.jpg", "transcriptions": {"f0": "Balboa HC", "f1": "7/22", "f2": "8", "f3": "Robert. J. Atherley", "f6": "20000", "f7": "21301", "f8": "Record", "f10": "June 26th 1905", "f11": "Messenger", "f13": "55", "f14": "May 1.st", "f15": "8", "f18": "yes.", "f19": "Barbadors", "f20": "Feb 11. 1885", "f21": "Barbadrse B.", "f22": "Balboa", "f23": "LaBoca", "f24": "June 26th 1905", "f29": "Black", "f30": "yes", "f31": "yes", "f34": "5", "f35": "3", "f36": "137", "f37": "scar on left thumb back of first joint", "f44": "329", "f48": "Nov 11 1918", "f49": "Am", "f50": "Nov 11 1918", "f51": "Am"}}